flintrock/__init__.py
flintrock/__main__.py
flintrock/config.yaml.template
flintrock/core.py
flintrock/ec2.py
flintrock/exceptions.py
flintrock/flintrock.py
flintrock/services.py
flintrock/ssh.py
flintrock/util.py
flintrock/scripts/adoptium.repo
flintrock/scripts/download-package.py
flintrock/scripts/setup-ephemeral-storage.py
flintrock/templates/hadoop/conf/core-site.xml
flintrock/templates/hadoop/conf/hadoop-env.sh
flintrock/templates/hadoop/conf/hdfs-site.xml
flintrock/templates/hadoop/conf/masters
flintrock/templates/hadoop/conf/slaves
flintrock/templates/spark/conf/slaves
flintrock/templates/spark/conf/spark-env.sh
Flintrock-2.1.0.dist-info/LICENSE
Flintrock-2.1.0.dist-info/METADATA
Flintrock-2.1.0.dist-info/WHEEL
Flintrock-2.1.0.dist-info/entry_points.txt
Flintrock-2.1.0.dist-info/top_level.txt
Flintrock-2.1.0.dist-info/RECORD
