Metadata-Version: 2.1
Name: Flintrock
Version: 2.1.0
Summary: A command-line tool for launching Apache Spark clusters.
Home-page: https://github.com/nchammas/flintrock
Author: Nicholas Chammas
Author-email: nicholas.chammas@gmail.com
License: Apache License 2.0
Keywords: Apache Spark
Classifier: Development Status :: 5 - Production/Stable
Classifier: Intended Audience :: Developers
Classifier: Intended Audience :: Science/Research
Classifier: Topic :: Utilities
Classifier: Environment :: Console
Classifier: Operating System :: MacOS :: MacOS X
Classifier: Operating System :: POSIX
Classifier: License :: OSI Approved :: Apache Software License
Classifier: Programming Language :: Python :: 3
Classifier: Programming Language :: Python :: 3 :: Only
Requires-Python: >= 3.8
License-File: LICENSE
Requires-Dist: boto3 ==1.29.4
Requires-Dist: botocore ==1.32.4
Requires-Dist: click ==8.1.7
Requires-Dist: paramiko ==3.3.1
Requires-Dist: PyYAML ==6.0.1
